Metadata-Version: 1.1
Name: exampleJupyter
Version: 1.0.0
Summary: ML example
Home-page: UNKNOWN
Author: Jose Romero
Author-email: josedelvalle83@gmail.com
License: MIT
Keywords: example machine learning
Platform: UNKNOWN
Classifier: Development Status :: 3 - Alpha
Classifier: Intended Audience :: Developers
Classifier: Topic :: Software Development :: Build Tools
Classifier: License :: OSI Approved :: MIT License
Classifier: Programming Language :: Python :: 2.7
